ddmonitoring/__init__.py
ddmonitoring/__main__.py
ddmonitoring/dd.png
ddmonitoring/main.py
ddmonitoring/monitoring.py
ddmonitoring/run.py
ddmonitoring/app/__init__.py
ddmonitoring/app/metrics_model.py
ddmonitoring/app/view.py
ddmonitoring/folder/__init__.py
ddmonitoring/utils/UI.py
ddmonitoring/utils/__init__.py
ddmonitoring/utils/constants.py
ddmonitoring/utils/custom_parser.py
ddmonitoring/utils/helpers.py
ddmonitoring/utils/metrics_model.py
ddmonitoring/utils/monitoring_bot.py
ddmonitoring/utils/start.py
ddmonitoring/utils/view.py
tests/integration/__init__.py
tests/integration/monitoring_int_test.py
tests/unit/__init__.py
tests/unit/monitoring_test.py
ddmonitoring-0.1.dist-info/METADATA
ddmonitoring-0.1.dist-info/WHEEL
ddmonitoring-0.1.dist-info/entry_points.txt
ddmonitoring-0.1.dist-info/namespace_packages.txt
ddmonitoring-0.1.dist-info/top_level.txt
ddmonitoring-0.1.dist-info/RECORD
